{
    "custom_dungeon": {
        "dungeon_guid": "12884901888",
        "dungeon_id": 2114,
        "first_publish_time": 0,
        "is_liked": false,
        "room_list": [
            {
                "block_list": [
                    {
                        "block_id": 3001,
                        "guid": 14020,
                        "pos": {
                            "x": 7,
                            "y": 17,
                            "z": 6
                        },
                        "rot": {
                            "x": 0,
                            "y": 90,
                            "z": 0
                        }
                    },
                    {
                        "block_id": 5003,
                        "guid": 11006,
                        "pos": {
                            "x": 11,
                            "y": 10,
                            "z": 13
                        },
                        "rot": {
                            "x": 0,
                            "y": 0,
                            "z": 0
                        }
                    },
                    {
                        "block_id": 3001,
                        "guid": 14019,
                        "pos": {
                            "x": 21,
                            "y": 17,
                            "z": 14
                        },
                        "rot": {
                            "x": 0,
                            "y": 45,
                            "z": 0
                        }
                    },
                    {
                        "block_id": 5003,
                        "guid": 10002,
                        "pos": {
                            "x": 21,
                            "y": 0,
                            "z": 13
                        },
                        "rot": {
                            "x": 0,
                            "y": 0,
                            "z": 0
                        }
                    },
                    {
                        "block_id": 1002,
                        "guid": 14021,
                        "pos": {
                            "x": 3,
                            "y": 17,
                            "z": 7
                        },
                        "rot": {
                            "x": 0,
                            "y": 0,
                            "z": 0
                        }
                    },
                    {
                        "block_id": 2003,
                        "guid": 11008,
                        "pos": {
                            "x": 5,
                            "y": 7,
                            "z": 22
                        },
                        "rot": {
                            "x": 0,
                            "y": 0,
                            "z": 0
                        }
                    },
                    {
                        "block_id": 2003,
                        "guid": 10003,
                        "pos": {
                            "x": 15,
                            "y": 0,
                            "z": 14
                        },
                        "rot": {
                            "x": 0,
                            "y": 0,
                            "z": 0
                        }
                    },
                    {
                        "block_id": 2003,
                        "guid": 10004,
                        "pos": {
                            "x": 10,
                            "y": 5,
                            "z": 14
                        },
                        "rot": {
                            "x": 0,
                            "y": 0,
                            "z": 0
                        }
                    },
                    {
                        "block_id": 3006,
                        "guid": 13017,
                        "pos": {
                            "x": 15,
                            "y": 14,
                            "z": 20
                        },
                        "rot": {
                            "x": 0,
                            "y": 0,
                            "z": 0
                        }
                    },
                    {
                        "block_id": 1001,
                        "guid": 15023,
                        "pos": {
                            "x": 0,
                            "y": 0,
                            "z": 12
                        },
                        "rot": {
                            "x": 0,
                            "y": 0,
                            "z": 0
                        }
                    },
                    {
                        "block_id": 2003,
                        "guid": 12010,
                        "pos": {
                            "x": 10,
                            "y": 12,
                            "z": 22
                        },
                        "rot": {
                            "x": 0,
                            "y": 0,
                            "z": 0
                        }
                    },
                    {
                        "block_id": 1002,
                        "guid": 12011,
                        "pos": {
                            "x": 13,
                            "y": 17,
                            "z": 21
                        },
                        "rot": {
                            "x": 0,
                            "y": 0,
                            "z": 0
                        }
                    },
                    {
                        "block_id": 2002,
                        "guid": 12013,
                        "pos": {
                            "x": 21,
                            "y": 17,
                            "z": 20
                        },
                        "rot": {
                            "x": 0,
                            "y": 0,
                            "z": 0
                        }
                    },
                    {
                        "block_id": 1002,
                        "guid": 12014,
                        "pos": {
                            "x": 22,
                            "y": 18,
                            "z": 21
                        },
                        "rot": {
                            "x": 0,
                            "y": 0,
                            "z": 0
                        }
                    }
                ],
                "room_id": 1
            }
        ],
        "setting": {
            "coin_limit": 3,
            "is_arrive_finish": true,
            "is_forbid_skill": true,
            "life_num": 3,
            "open_room_list": [
                1
            ],
            "start_room_id": 0,
            "time_limit": 60
        },
        "version": 0
    },
    "dungeon_brief": {
        "abstract": {
            "brick_statistics_map": {
                "1001": 1,
                "1002": 3,
                "3001": 2,
                "3006": 1,
                "5003": 2
            },
            "finish_room_id": 1,
            "first_publish_time": 1640598396,
            "last_publish_time": 1640598396,
            "total_coin_num": 3
        },
        "creator_nickname": "sda",
        "dungeon_guid": "34359749176",
        "dungeon_id": 2114,
        "is_need_recommend": true,
        "recommend_type": 1,
        "setting": {
            "coin_limit": 3,
            "is_arrive_finish": true,
            "is_forbid_skill": true,
            "life_num": 3,
            "open_room_list": [
                1
            ],
            "start_room_id": 0,
            "time_limit": 60
        },
        "tag_list": []
    }
}