<root entry_id="main">
	<BehaviorTree ID="main">
		<Selector>
			<Sequence>
				<Condition name="ConditionCheckIsRerollPhase" desc="是否是重投阶段" />
				<Action name="DoPassNode" />
			</Sequence>
			<Sequence>
				<Condition name="ConditionCheckIsActionPhase" desc="是否是行动阶段" />
				
				<Action name="ActionGenPlayCardPlan" param1="GCG_TAG_ARTIFACT" param2="1" param3="200" param4="SPECIFY:3;SAME:2;COST_VOID:1;RECHARGE:10" param5="-50" param6="-50"/>
				<Action name="ActionGenPlayCardPlan" param1="GCG_TAG_WEAPON" param2="1" param3="190" param4="SPECIFY:3;SAME:2;COST_VOID:1;RECHARGE:10" param5="-50" param6="-50"/>
				<Action name="ActionGenPlayCardPlan" param1="GCG_TAG_TALENT" param2="2" param3="170" param4="SPECIFY:3;SAME:2;COST_VOID:1;RECHARGE:10"/>

				<Action name="ActionGenCharacterPlan" param1="GCG_SKILL_TAG_Q" param2="180"  param3="SPECIFY:3;SAME:3;COST_VOID:-30"/>
				<Action name="ActionGenChangeToCanAttackCharacter" param1="GCG_SKILL_TAG_Q" param2="170"  param3="SPECIFY:3;SAME:3;COST_VOID:-30"/>
				<Action name="ActionGenCharacterPlan" param1="" param2="160"  param3="SPECIFY:3;SAME:3;COST_VOID:-30"/>
				<Action name="ActionGenChangeToCanAttackCharacter" param1="" param2="150"  param3="SPECIFY:3;SAME:3;COST_VOID:-30"/>
				
				<Action name="ActionGenRebootPlan" param1="1" param2=""  param3="3"  param4="120" param5="SPECIFY:2;SAME:2;RECHARGE:-10;COST_VOID:2"/>

				<Action name="ActionGenPlayCardPlan" param1="" param2="2" param3="0" param4="SPECIFY:3;SAME:2;RECHARGE:2;COST_VOID:1" param5="-50" param6="-50"/>
				<Action name="ActionGenChangeCharacterPlan" param1="BEHAVIOR_CONFIG_CHANGE_CHARACTER_SORT_TYPE_MAX_HP" param2="0" param3="-1000"/>

				<Action name="ActionSortAndExecPlan" />
			</Sequence>
			<Sequence>
				<Condition name="ConditionCheckIsSelectOnstageCharacterPhase" desc="是否是换人" />
				<Action name="DoPassNode" />
			</Sequence>
			<Sequence>
				<Condition name="ConditionCheckIsDrawPhase" desc="是否是更换手牌" />
				
				<Action name="ActionReserveHandCardByTag" param1="GCG_TAG_RESONANCE" param2="2" param3="SPECIFY:3;SAME:3;COST_VOID:3" param4="0" />
				<Action name="ActionReserveHandCardByTag" param1="GCG_TAG_ARTIFACT" param2="2" param3="SPECIFY:3;SAME:3;COST_VOID:3" param4="0" />
				<Action name="ActionReserveHandCardByTag" param1="GCG_TAG_TALENT" param2="2" param3="SPECIFY:3;SAME:3;COST_VOID:3" param4="0" />

				<Action name="ActionReserveHandCardByTag" param1="GCG_TAG_WEAPON" param2="1" param3="SPECIFY:3;SAME:3;COST_VOID:3" param4="0" />
				<Action name="ActionReserveHandCardByTag" param1="GCG_TAG_ITEM" param2="1" param3="SPECIFY:3;SAME:3;COST_VOID:3" param4="0" />
				<Action name="ActionReserveHandCardByTag" param1="GCG_TAG_ALLY" param2="1" param3="SPECIFY:3;SAME:3;COST_VOID:3" param4="0" />
				<Action name="ActionReserveHandCardByTag" param1="GCG_TAG_PLACE" param2="1" param3="SPECIFY:3;SAME:3;COST_VOID:3" param4="0" />

				<Action name="ActionRedraw" />
			</Sequence>
		</Selector>
	</BehaviorTree>
</root>
